hattori/__init__.py
hattori/base.py
hattori/constants.py
hattori/exceptions.py
hattori/utils.py
hattori/management/__init__.py
hattori/management/commands/__init__.py
hattori/management/commands/anonymize_db.py
django_hattori-0.2.1.dist-info/AUTHORS
django_hattori-0.2.1.dist-info/LICENSE
django_hattori-0.2.1.dist-info/METADATA
django_hattori-0.2.1.dist-info/WHEEL
django_hattori-0.2.1.dist-info/top_level.txt
django_hattori-0.2.1.dist-info/RECORD
