Metadata-Version: 2.1
Name: django-hattori
Version: 0.2.1
Summary: Command to anonymize sensitive data.
Home-page: https://github.com/APSL/django-hattori
Author: Marc Galofré
Author-email: mgalofre@apsl.net
License: UNKNOWN
Platform: UNKNOWN
Classifier: Environment :: Web Environment
Classifier: Intended Audience :: Developers
Classifier: Programming Language :: Python
Classifier: Programming Language :: Python :: 3
Classifier: Programming Language :: Python :: 3.5
Classifier: Operating System :: OS Independent
Classifier: Topic :: Software Development
Requires-Dist: Django (>=1.8)
Requires-Dist: django-bulk-update (>=2.2.0)
Requires-Dist: Faker (>=0.8.13)
Requires-Dist: six
Requires-Dist: tqdm (>=4.23.4)
